django_smart_redis
